workshop_schedules/__init__.py
workshop_schedules/_version.py
workshop_schedules/cli.py
workshop_schedules/tools.py
workshop_schedules-0.0.1.dist-info/AUTHORS.md
workshop_schedules-0.0.1.dist-info/LICENSE
workshop_schedules-0.0.1.dist-info/METADATA
workshop_schedules-0.0.1.dist-info/WHEEL
workshop_schedules-0.0.1.dist-info/entry_points.txt
workshop_schedules-0.0.1.dist-info/top_level.txt
workshop_schedules-0.0.1.dist-info/RECORD
